arctic_inference/__init__.py
arctic_inference/common/__init__.py
arctic_inference/common/swiftkv/__init__.py
arctic_inference/common/swiftkv/configs.py
arctic_inference/vllm/__init__.py
arctic_inference/vllm/model_runner.py
arctic_inference/vllm/plugins.py
arctic_inference/vllm/swiftkv/__init__.py
arctic_inference/vllm/swiftkv/llama_swiftkv.py
arctic_inference-0.0.4.dist-info/licenses/LICENSE
arctic_inference-0.0.4.dist-info/METADATA
arctic_inference-0.0.4.dist-info/WHEEL
arctic_inference-0.0.4.dist-info/entry_points.txt
arctic_inference-0.0.4.dist-info/top_level.txt
arctic_inference-0.0.4.dist-info/RECORD
